pysanet/__init__.py
pysanet/__main__.py
pysanet/api.py
pysanet/cli/__init__.py
pysanet/cli/commands.py
pysanet/cli/utils.py
pysanet/core.py
pysanet/enums.py
pysanet/exceptions.py
pysanet/schemas/__init__.py
pysanet/schemas/models.py
pysanet/schemas/outs.py
pysanet/settings.py
pysanet-0.1.1.dist-info/LICENSE
pysanet-0.1.1.dist-info/METADATA
pysanet-0.1.1.dist-info/WHEEL
pysanet-0.1.1.dist-info/entry_points.txt
pysanet-0.1.1.dist-info/RECORD
